efshape/__init__.py
efshape/efa.py
efshape/efgui.py
efshape/fgui.py
efshape-1.0.0.dist-info/METADATA
efshape-1.0.0.dist-info/WHEEL
efshape-1.0.0.dist-info/entry_points.txt
efshape-1.0.0.dist-info/top_level.txt
efshape-1.0.0.dist-info/RECORD
